words_count/__init__.py
words_count/main.py
words_count/parser.py
words_count-1.0.0.dist-info/METADATA
words_count-1.0.0.dist-info/WHEEL
words_count-1.0.0.dist-info/entry_points.txt
words_count-1.0.0.dist-info/top_level.txt
words_count-1.0.0.dist-info/RECORD
