Metadata-Version: 2.1
Name: words-count
Version: 1.0.0
Summary: CLI tool for that outputs the N (N by default 100) most common n-word (n by default is 3)
Home-page: https://github.com/javibravo/words-count
Author: Javier Bravo
Author-email: javibravo85@gmail.com
License: MIT
Keywords: count word words text
Platform: UNKNOWN
Classifier: Programming Language :: Python
Classifier: Programming Language :: Python :: 3
Classifier: Environment :: Console
Classifier: Natural Language :: English
Classifier: Operating System :: Unix
Classifier: Operating System :: MacOS
Classifier: License :: OSI Approved :: MIT License
